finschool
