Metadata-Version: 1.1
Name: finschool
Version: 0.0.3
Summary: This projects are meant for study
Home-page: https://github.com/Boronium/finschool
Author: Fin
Author-email: finpunyapat66@gmail.com
License: MIT
Download-URL: https://github.com/Boronium/finschool/archive/refs/tags/v0.0.3.zip
Keywords: OOP,School,Uncle Engineer
Platform: UNKNOWN
Classifier: Development Status :: 3 - Alpha
Classifier: Intended Audience :: Education
Classifier: Topic :: Software Development :: Build Tools
Classifier: License :: OSI Approved :: MIT License
Classifier: Programming Language :: Python :: 3
Classifier: Programming Language :: Python :: 3.4
Classifier: Programming Language :: Python :: 3.5
Classifier: Programming Language :: Python :: 3.6
Classifier: Programming Language :: Python :: 3.7
Classifier: Programming Language :: Python :: 3.8
Classifier: Programming Language :: Python :: 3.9
